ratapi/__init__.py
ratapi/classlist.py
ratapi/controls.py
ratapi/eventManager.so
ratapi/events.py
ratapi/inputs.py
ratapi/models.py
ratapi/outputs.py
ratapi/project.py
ratapi/rat_core.cpython-312-x86_64-linux-musl.so
ratapi/run.py
ratapi/wrappers.py
ratapi/examples/__init__.py
ratapi/examples/absorption/__init__.py
ratapi/examples/absorption/absorption.py
ratapi/examples/absorption/volume_thiol_bilayer.py
ratapi/examples/convert_rascal_project/Model_IIb.py
ratapi/examples/convert_rascal_project/__init__.py
ratapi/examples/convert_rascal_project/convert_rascal.py
ratapi/examples/data/D2O_spin_down.dat
ratapi/examples/data/D2O_spin_up.dat
ratapi/examples/data/DSPC_D2O.dat
ratapi/examples/data/DSPC_SMW.dat
ratapi/examples/data/H2O_spin_down.dat
ratapi/examples/data/H2O_spin_up.dat
ratapi/examples/data/__init__.py
ratapi/examples/data/c_PLP0016596.dat
ratapi/examples/data/c_PLP0016601.dat
ratapi/examples/data/c_PLP0016607.dat
ratapi/examples/data/d2o_background_data.dat
ratapi/examples/domains/__init__.py
ratapi/examples/domains/alloy_domains.py
ratapi/examples/domains/domains_XY_model.py
ratapi/examples/domains/domains_custom_XY.py
ratapi/examples/domains/domains_custom_layers.py
ratapi/examples/domains/domains_standard_layers.py
ratapi/examples/languages/__init__.py
ratapi/examples/languages/custom_bilayer.py
ratapi/examples/languages/run_custom_file_languages.py
ratapi/examples/languages/setup_problem.py
ratapi/examples/normal_reflectivity/DSPC_custom_XY.py
ratapi/examples/normal_reflectivity/DSPC_custom_layers.py
ratapi/examples/normal_reflectivity/DSPC_data_background.py
ratapi/examples/normal_reflectivity/DSPC_function_background.py
ratapi/examples/normal_reflectivity/DSPC_standard_layers.py
ratapi/examples/normal_reflectivity/__init__.py
ratapi/examples/normal_reflectivity/background_function.py
ratapi/examples/normal_reflectivity/custom_XY_DSPC.py
ratapi/examples/normal_reflectivity/custom_bilayer_DSPC.py
ratapi-0.0.0.dev11.dist-info/METADATA
ratapi-0.0.0.dev11.dist-info/WHEEL
ratapi-0.0.0.dev11.dist-info/top_level.txt
ratapi-0.0.0.dev11.dist-info/RECORD
